asanak_sms_client/__init__.py
asanak_sms_client/client.py
asanak_sms_client/exceptions.py
asanak_sms_client-0.1.4.dist-info/LICENSE
asanak_sms_client-0.1.4.dist-info/METADATA
asanak_sms_client-0.1.4.dist-info/WHEEL
asanak_sms_client-0.1.4.dist-info/top_level.txt
asanak_sms_client-0.1.4.dist-info/RECORD
