Metadata-Version: 2.1
Name: asanak-sms-client
Version: 0.1.4
Summary: Asanak SMS client for sending and reporting messages via REST API
Author: Farzad Forouzanfar
Author-email: forouzanfar2000f@gmail.com
Classifier: Programming Language :: Python :: 3
Classifier: License :: OSI Approved :: MIT License
Classifier: Operating System :: OS Independent
Requires-Python: >=3.7
License-File: LICENSE
Requires-Dist: requests>=2.25
